setup.py
django_jquery_tipsy.egg-info/PKG-INFO
django_jquery_tipsy.egg-info/SOURCES.txt
django_jquery_tipsy.egg-info/dependency_links.txt
django_jquery_tipsy.egg-info/requires.txt
django_jquery_tipsy.egg-info/top_level.txt
jquery_tipsy/__init__.py
jquery_tipsy/models.py
jquery_tipsy/static/css/tipsy.css
jquery_tipsy/static/js/jquery.tipsy.js