Metadata-Version: 1.1
Name: django-jquery-tipsy
Version: 1.0.0a
Summary: jQuery tipsy plugin packaged in a django app to speed up new applications and deployment.
Home-page: https://github.com/mikebryant/django-jquery-tipsy
Author: Mike Bryant
Author-email: mike@mikebryant.me.uk
License: MIT
Keywords: django,jquery,tipsy,staticfiles
Platform: any
Classifier: Development Status :: 5 - Production/Stable
Classifier: Environment :: Web Environment
Classifier: Framework :: Django
Classifier: Intended Audience :: Developers
Classifier: Natural Language :: English
Classifier: License :: OSI Approved :: MIT License
Classifier: Operating System :: OS Independent
Classifier: Programming Language :: Python
Classifier: Topic :: Utilities
